coalib/VERSION
coalib/__init__.py
coalib/coala.py
coalib/coala_ci.py
coalib/coala_delete_orig.py
coalib/coala_format.py
coalib/coala_json.py
coalib/coala_main.py
coalib/coala_modes.py
coalib/system_coafile
coalib/bearlib/__init__.py
coalib/bearlib/abstractions/ExternalBearWrap.py
coalib/bearlib/abstractions/Linter.py
coalib/bearlib/abstractions/LinterClass.py
coalib/bearlib/abstractions/SectionCreatable.py
coalib/bearlib/abstractions/__init__.py
coalib/bearlib/aspects/Formatting.py
coalib/bearlib/aspects/Metadata.py
coalib/bearlib/aspects/Redundancy.py
coalib/bearlib/aspects/Security.py
coalib/bearlib/aspects/Smell.py
coalib/bearlib/aspects/Spelling.py
coalib/bearlib/aspects/__init__.py
coalib/bearlib/aspects/base.py
coalib/bearlib/aspects/collections.py
coalib/bearlib/aspects/decorators.py
coalib/bearlib/aspects/docs.py
coalib/bearlib/aspects/exceptions.py
coalib/bearlib/aspects/meta.py
coalib/bearlib/aspects/root.py
coalib/bearlib/aspects/taste.py
coalib/bearlib/languages/Language.py
coalib/bearlib/languages/LanguageDefinition.py
coalib/bearlib/languages/__init__.py
coalib/bearlib/languages/definitions/Bash.py
coalib/bearlib/languages/definitions/C.py
coalib/bearlib/languages/definitions/CPP.py
coalib/bearlib/languages/definitions/CSS.py
coalib/bearlib/languages/definitions/CSharp.py
coalib/bearlib/languages/definitions/D.py
coalib/bearlib/languages/definitions/DOT.py
coalib/bearlib/languages/definitions/Dart.py
coalib/bearlib/languages/definitions/Fortran.py
coalib/bearlib/languages/definitions/Golang.py
coalib/bearlib/languages/definitions/GraphQL.py
coalib/bearlib/languages/definitions/Haskell.py
coalib/bearlib/languages/definitions/JSON.py
coalib/bearlib/languages/definitions/JSP.py
coalib/bearlib/languages/definitions/Java.py
coalib/bearlib/languages/definitions/JavaScript.py
coalib/bearlib/languages/definitions/Jinja2.py
coalib/bearlib/languages/definitions/KornShell.py
coalib/bearlib/languages/definitions/Markdown.py
vyd_coala-0.12.0.dev99999999999999.dist-info/LICENSE
vyd_coala-0.12.0.dev99999999999999.dist-info/METADATA
vyd_coala-0.12.0.dev99999999999999.dist-info/WHEEL
vyd_coala-0.12.0.dev99999999999999.dist-info/dependency_links.txt
vyd_coala-0.12.0.dev99999999999999.dist-info/entry_points.txt
vyd_coala-0.12.0.dev99999999999999.dist-info/top_level.txt
vyd_coala-0.12.0.dev99999999999999.dist-info/RECORD
